forms_fieldset/__init__.py
forms_fieldset/admin.py
forms_fieldset/apps.py
forms_fieldset/models.py
forms_fieldset/tests.py
forms_fieldset/views.py
forms_fieldset/migrations/__init__.py
forms_fieldset/static/forms_fieldset/css/fonts.css
forms_fieldset/static/forms_fieldset/css/main.css
forms_fieldset/static/forms_fieldset/fonts/LICENSE.txt
forms_fieldset/static/forms_fieldset/fonts/README.txt
forms_fieldset/static/forms_fieldset/fonts/Roboto-Bold-webfont.woff
forms_fieldset/static/forms_fieldset/fonts/Roboto-Light-webfont.woff
forms_fieldset/static/forms_fieldset/fonts/Roboto-Regular-webfont.woff
forms_fieldset/static/forms_fieldset/img/icon-addlink.svg
forms_fieldset/static/forms_fieldset/img/inline-delete.svg
forms_fieldset/templates/forms_fieldset/fieldset.html
forms_fieldset/templates/forms_fieldset/tabular.html
forms_fieldset/templatetags/__init__.py
forms_fieldset/templatetags/forms_fieldset.py
django_forms_fieldset-1.0.1.dist-info/LICENSE
django_forms_fieldset-1.0.1.dist-info/METADATA
django_forms_fieldset-1.0.1.dist-info/WHEEL
django_forms_fieldset-1.0.1.dist-info/top_level.txt
django_forms_fieldset-1.0.1.dist-info/RECORD
