Metadata-Version: 2.1
Name: django-forms-fieldset
Version: 1.0.1
Summary: Django form fieldset inspire django admin fieldset.
Home-page: https://github.com/hadpro24/django-forms-fieldset
Author: Harouna Diallo
Author-email: dev.harouna@gmail.com
License: BSD-3-Clause
Platform: UNKNOWN
Classifier: Environment :: Console
Classifier: Intended Audience :: Developers
Classifier: License :: OSI Approved :: BSD License
Classifier: Operating System :: OS Independent
Classifier: Programming Language :: Python :: 3
Classifier: Programming Language :: Python :: 3 :: Only
Classifier: Programming Language :: Python :: 3.6
Classifier: Programming Language :: Python :: 3.7
Classifier: Programming Language :: Python :: 3.8
License-File: LICENSE
